spbnet/__init__.py
spbnet/config.finetune.yaml
spbnet/config.predict.yaml
spbnet/config.pretrain.yaml
spbnet/finetune.py
spbnet/predict.py
spbnet/pretrain.py
spbnet/cli/__init__.py
spbnet/cli/attn.py
spbnet/cli/buildAtomGrid.py
spbnet/cli/buildData.py
spbnet/cli/buildModalData.py
spbnet/cli/calcAtomNum.py
spbnet/cli/calcMeanStd.py
spbnet/cli/checkData.py
spbnet/cli/filterData.py
spbnet/cli/installMake.py
spbnet/cli/main.py
spbnet/cli/makeGriday.py
spbnet/cli/uninstallGriday.py
spbnet/data/__init__.py
spbnet/data/buildAtomGrid.py
spbnet/data/buildData.py
spbnet/data/calcAtomNum.py
spbnet/data/calcMeanStd.py
spbnet/data/checkData.py
spbnet/data/dataset.py
spbnet/data/dataset_feat.py
spbnet/data/dataset_predict.py
spbnet/data/dataset_pretrain.py
spbnet/data/filterData.py
spbnet/data/float2int8.py
spbnet/data/install_griday.py
spbnet/data/prepare_data.py
spbnet/data/libs/GRIDAY/AtomTypeMap.cpp
spbnet/data/libs/GRIDAY/AtomTypeMap.hpp
spbnet/data/libs/GRIDAY/AtomTypeMap.o
spbnet/data/libs/GRIDAY/Cell.hpp
spbnet/data/libs/GRIDAY/ChannelAnalyzer.cpp
spbnet/data/libs/GRIDAY/ChannelAnalyzer.hpp
spbnet/data/libs/GRIDAY/ChannelAnalyzer.o
spbnet/data/libs/GRIDAY/EnergyGrid.cpp
spbnet/data/libs/GRIDAY/EnergyGrid.cpp-backup
spbnet/data/libs/GRIDAY/EnergyGrid.hpp
spbnet/data/libs/GRIDAY/EnergyGrid.o
spbnet/data/libs/GRIDAY/ForceField.cpp
spbnet/data/libs/GRIDAY/ForceField.hpp
spbnet/data/libs/GRIDAY/ForceField.o
spbnet/data/libs/GRIDAY/FourierAnalyzer.cpp
spbnet/data/libs/GRIDAY/FourierAnalyzer.hpp
spbnet/data/libs/GRIDAY/FourierAnalyzer.o
spbnet/data/libs/GRIDAY/Framework.cpp
spbnet/data/libs/GRIDAY/Framework.hpp
spbnet/data/libs/GRIDAY/Framework.o
spbnet/data/libs/GRIDAY/Gaussian.cpp
spbnet/data/libs/GRIDAY/Gaussian.hpp
spbnet/data/libs/GRIDAY/Gaussian.o
spbnet/data/libs/GRIDAY/GridMaker.cpp
spbnet/data/libs/GRIDAY/GridMaker.hpp
spbnet/data/libs/GRIDAY/GridMaker.o
spbnet/data/libs/GRIDAY/Griday.hpp
spbnet/data/libs/GRIDAY/GridayException.cpp
spbnet-0.0.26.dist-info/LICENSE.txt
spbnet-0.0.26.dist-info/METADATA
spbnet-0.0.26.dist-info/WHEEL
spbnet-0.0.26.dist-info/entry_points.txt
spbnet-0.0.26.dist-info/top_level.txt
spbnet-0.0.26.dist-info/RECORD
