Metadata-Version: 2.1
Name: spbnet
Version: 0.0.26
Summary: spbnet
Home-page: https://tyvanzou.github.io/spbnet/
Download-URL: https://github.com/tyvanzou/spbnet
Author: Jiawen Zou
Author-email: 20307130189@fudan.edu.cn
License-File: LICENSE.txt
Requires-Dist: ase ==3.22.1
Requires-Dist: matplotlib ==3.7.5
Requires-Dist: numpy ==1.24.4
Requires-Dist: pandas ==2.0.3
Requires-Dist: pymatgen ==2023.8.10
Requires-Dist: requests ==2.31.0
Requires-Dist: scipy ==1.10.1
Requires-Dist: tqdm ==4.66.2
Requires-Dist: torch ==2.2.2
Requires-Dist: lightning ==2.2.1
Requires-Dist: transformers ==4.39.1
Requires-Dist: einops ==0.7.0
Requires-Dist: timm ==0.9.16
Requires-Dist: tensorboard ==2.14.0
Requires-Dist: scikit-learn ==1.3.2
Requires-Dist: seaborn ==0.13.2
Requires-Dist: colorama ==0.4.6
